MANIFEST.in
README.rst
setup.py
smorgasbord/__init__.py
smorgasbord/coverage.py
smorgasbord/language.py
smorgasbord/language_parser.py
smorgasbord/report.py
smorgasbord/reporter.py
smorgasbord/smorgasbord.py
smorgasbord.egg-info/PKG-INFO
smorgasbord.egg-info/SOURCES.txt
smorgasbord.egg-info/dependency_links.txt
smorgasbord.egg-info/requires.txt
smorgasbord.egg-info/top_level.txt
test/test_coverage.py
test/test_language.py
test/test_language_parser.py
test/test_report.py
test/test_reporter.py
test/test_smorgasbord.py