Metadata-Version: 1.0
Name: smorgasbord
Version: 0.0.2
Summary: Reports language coverage given a set of unicode values
Home-page: http://github.com/jackjennings/smorgasbord
Author: Jack Jennings
Author-email: j@ckjennin.gs
License: MIT
Platform: UNKNOWN
